README.md
setup.py
uns/__init__.py
uns/cache.py
uns/cli.py
uns/constants.py
uns/http.py
uns/protocol.py
uns.egg-info/PKG-INFO
uns.egg-info/SOURCES.txt
uns.egg-info/dependency_links.txt
uns.egg-info/entry_points.txt
uns.egg-info/requires.txt
uns.egg-info/top_level.txt