Metadata-Version: 2.1
Name: uns
Version: 1.4.0
Summary: UNKNOWN
Home-page: UNKNOWN
License: MIT
Platform: UNKNOWN
